{ "frontend" : [
    {
        "name": "REACT",
        "img_src": "/react3.png"
    }, 
    {
        "name": "REDUX",
        "img_src": "/Redux.png"
    },
    {
        "name": "NEXTJS",
        "img_src": "/nextjs.png"
    },
    {
        "name": "TAILWIND",
        "img_src": "/Tailwindcss.png"
    },
    {
        "name": "HTML",
        "img_src": "/html5.png"
    },     
    {
        "name": "CSS",
        "img_src": "/cssLogo.png"
    },    
    {
        "name": "JAVASCRIPT",
        "img_src": "/javascript.png"
    }],
    "backend": [    
    {
        "name": "NODEJS",
        "img_src": "/nodejsLogo.jpg"
    },   
    {
        "name": "SOLIDITY",
        "img_src": "/solidity.png"
    },    
    {
        "name": "PYTHON",
        "img_src": "/python.png"
    },    
    {
        "name": "HARDHAT",
        "img_src": "/hardhat.png"
    },    
    {
        "name": "ETHERS",
        "img_src": "/ethers.png"
    },    
    {
        "name": "EXPRESSJS",
        "img_src": "/expressjs.png"
    },
    {
        "name": "GOLANG",
        "img_src": "/GoLogo.png"
    }],
    "database":[     
    {
        "name": "POSTGRESQL",
        "img_src": "/postgresql.jpg"
    },    
    {
        "name": "GRAPHQL",
        "img_src": "/graphql.png"
    },
    {
        "name": "MONGODB",
        "img_src": "/MongoDBLogo.png"
    }]
}
